{
    "urunler": [
        {
            "id": 01,
            "isim": "Cold Blooded Creepz #1088",
            "kategori": "art",
            "fiyat": "10.00",
            "resim": "https://drive.google.com/file/d/112PpsmWZWQ-TXagk5H_hRQ4C2AaIdc0r"
        },
        {
            "id": 02,
            "isim": "Cold Blooded Creepz #1011",
            "kategori": "item",
            "fiyat": "20.00",
            "resim": "https://drive.google.com/file/d/10-I391z-zeTDl8WrwOpd60opSlXUK9BG"
        },
        {
            "id": 03,
            "isim": "Cold Blooded Creepz #1073",
            "kategori": "land",
            "fiyat": "30.00",
            "resim": "https://drive.google.com/file/d/1-bwLnO1xnoJlqLiaHftRHMnWL0QY2KLp"
        }
    ],
    "success": true
}
